{"id":"20200812_153924_ssc3d2_0013","type":"Feature","geometry":{"coordinates":[[[-77.02928899244945,42.8848932512207],[-77.02904804550037,42.8755502933769],[-76.99653595617055,42.87837830387184],[-76.99675688500429,42.88772624845801],[-77.02928899244945,42.8848932512207]]],"type":"Polygon"},"properties":{"acquired":"2020-08-12T15:39:24.687Z","camera_id":"d2","clear_confidence_percent":95,"clear_percent":100,"cloud_cover":0,"cloud_percent":0,"ground_control":true,"gsd":0.82,"heavy_haze_percent":0,"item_type":"SkySatScene","light_haze_percent":0,"pixel_resolution":0.5,"provider":"skysat","published":"2020-08-12T19:42:33Z","publishing_stage":"finalized","quality_category":"standard","satellite_azimuth":59.4,"satellite_id":"SSC3","shadow_percent":0,"snow_ice_percent":0,"strip_id":"s103_20200812T153924Z","sun_azimuth":137.5,"sun_elevation":55.4,"updated":"2020-08-12T21:31:41Z","view_angle":27.6,"visible_confidence_percent":74,"visible_percent":100}}
